promptify/__init__.py
promptify/cli.py
promptify_cli-0.1.8.dist-info/METADATA
promptify_cli-0.1.8.dist-info/WHEEL
promptify_cli-0.1.8.dist-info/entry_points.txt
promptify_cli-0.1.8.dist-info/top_level.txt
promptify_cli-0.1.8.dist-info/RECORD
