Metadata-Version: 2.4
Name: promptify-cli
Version: 0.1.8
Summary: Interactive CLI to select files, generate markdown for LLM prompts, and copy it to the clipboard.
Author-email: Oliver Proudfoot <oliverproudfoot@gmail.com>
License-Expression: MIT
Project-URL: Repository, https://github.com/olliepro/promptify
Project-URL: Bug Tracker, https://github.com/olliepro/promptify/issues
Project-URL: Documentation, https://github.com/olliepro/promptify#readme
Keywords: cli,prompt,clipboard,llm,ai,developer-tools
Classifier: Development Status :: 4 - Beta
Classifier: Environment :: Console
Classifier: Intended Audience :: Developers
Classifier: Operating System :: OS Independent
Classifier: Programming Language :: Python :: 3
Classifier: Programming Language :: Python :: 3.8
Classifier: Programming Language :: Python :: 3.9
Classifier: Programming Language :: Python :: 3.10
Classifier: Programming Language :: Python :: 3.11
Classifier: Programming Language :: Python :: 3.12
Classifier: Programming Language :: Python :: 3.13
Classifier: Topic :: Software Development :: Build Tools
Classifier: Topic :: Text Processing
Classifier: Topic :: Utilities
Requires-Python: >=3.8
Requires-Dist: typer>=0.9.0
Requires-Dist: pyperclip>=1.8.0
Requires-Dist: gitignore-parser>=0.1.0
Requires-Dist: tiktoken>=0.4.0
Requires-Dist: nbformat>=5.0.0
Requires-Dist: nbconvert>=7.0.0
Requires-Dist: prompt_toolkit>=3.0.0
Requires-Dist: appdirs>=1.4.0
Requires-Dist: chardet>=4.0.0
